rstcheck_sphinx/__init__.py
rstcheck_sphinx/py.typed
rstcheck_sphinx-1.0.0.dist-info/LICENSE
rstcheck_sphinx-1.0.0.dist-info/WHEEL
rstcheck_sphinx-1.0.0.dist-info/METADATA
rstcheck_sphinx-1.0.0.dist-info/RECORD
